setup.py
asposebarcode.egg-info/PKG-INFO
asposebarcode.egg-info/SOURCES.txt
asposebarcode.egg-info/dependency_links.txt
asposebarcode.egg-info/requires.txt
asposebarcode.egg-info/top_level.txt
models/BarcodeReader.py
models/BarcodeResponseList.py
models/BinarizationHints.py
models/ChecksumValidation.py
models/ResponseMessage.py
models/SaaSposeResponse.py
models/__init__.py
test/__init__.py
test/test.py