Metadata-Version: 1.1
Name: asposebarcode
Version: 1.0.0
Summary: Aspose Cloud SDK for Python allows you to use Aspose API in your Python applications
Home-page: https://github.com/asposebarcode/Aspose_BarCode_Cloud/tree/master/SDKs/Aspose.BarCode_Cloud_SDK_for_Python
Author: Imran Anwar
Author-email: imranwar@gmail.com
License: UNKNOWN
Platform: UNKNOWN
Classifier: Programming Language :: Python
Classifier: Programming Language :: Python :: 2
Classifier: License :: OSI Approved :: MIT License
Classifier: Operating System :: OS Independent
